AUTHORS
HISTORY
LICENSE
MANIFEST.in
README.md
setup.cfg
setup.py
videoscene/__init__.py
videoscene/core.py
videoscene/scenedata.py
videoscene.egg-info/PKG-INFO
videoscene.egg-info/SOURCES.txt
videoscene.egg-info/dependency_links.txt
videoscene.egg-info/not-zip-safe
videoscene.egg-info/pbr.json
videoscene.egg-info/top_level.txt