Metadata-Version: 1.1
Name: videoscene
Version: 0.2.0
Summary: Parse scene release tags
Home-page: http://github.com/walidsa3d/videoscene
Author: Walid Saad
Author-email: walid.sa3d@gmail.com
License: MIT
Keywords: scene release tags
Platform: UNKNOWN
Classifier: Development Status :: 4 - Beta
Classifier: Environment :: Console
Classifier: Intended Audience :: Developers
Classifier: License :: OSI Approved :: MIT License
Classifier: Operating System :: Unix
Classifier: Programming Language :: Python :: 2.7
Classifier: Topic :: Utilities
